huracanpy/__init__.py
huracanpy/_accessor.py
huracanpy/_basins.py
huracanpy/_concat.py
huracanpy/_interp.py
huracanpy/_metpy.py
huracanpy/_subset.py
huracanpy/_data/__init__.py
huracanpy/_data/_csv.py
huracanpy/_data/_load.py
huracanpy/_data/_netcdf.py
huracanpy/_data/_save.py
huracanpy/_data/_tempestextremes.py
huracanpy/_data/ibtracs.py
huracanpy/_data/iris_tc.py
huracanpy/_data/old_hurdat.py
huracanpy/_data/track_files.py
huracanpy/_data/witrack.py
huracanpy/_data/_ibtracs_files/jtwc.csv
huracanpy/_data/_ibtracs_files/wmo.csv
huracanpy/_data/example_data/00012024050100_050_0005160_atl
huracanpy/_data/example_data/CHAZ_sample.nc
huracanpy/_data/example_data/ERA20C_TRACK_NATL_tcident.nc
huracanpy/_data/example_data/ERA5_1996_UZ.csv
huracanpy/_data/example_data/IRIS_NI_1000Y_n6.txt
huracanpy/_data/example_data/MIT_sample.nc
huracanpy/_data/example_data/STORM_DATA_NA_10_YEARS_0.txt
huracanpy/_data/example_data/TempestExtremes-sample.txt
huracanpy/_data/example_data/event_tracks_2017_ERA5.dat
huracanpy/_data/example_data/sample.csv
huracanpy/_data/example_data/sample.parquet
huracanpy/_data/example_data/tilt.dat
huracanpy/_data/example_data/tr_trs_pos.2day_addT63vor_addmslp_add925wind_add10mwind.nolat.tcident.hart_sample
huracanpy/_data/example_data/tr_trs_pos.2day_addT63vor_addmslp_add925wind_add10mwind.tcident.new
huracanpy/_data/example_data/tr_trs_pos.2day_addT63vor_addmslp_add925wind_add10mwind.tcident.new.nc
huracanpy/assess/__init__.py
huracanpy/assess/_match.py
huracanpy/assess/_overlap.py
huracanpy/assess/_scores.py
huracanpy/calc/__init__.py
huracanpy/calc/_density.py
huracanpy/calc/_lifecycle.py
huracanpy/calc/_rates.py
huracanpy/calc/_track_stats.py
huracanpy/calc/_translation.py
huracanpy/info/__init__.py
huracanpy/info/_category.py
huracanpy/info/_geography.py
huracanpy/info/_time.py
huracanpy/info/_utils.py
huracanpy/plot/__init__.py
huracanpy/plot/_density.py
huracanpy/plot/_doughnut.py
huracanpy/plot/_fancyline.py
huracanpy/plot/_tracks.py
huracanpy-1.3.0.dist-info/licenses/LICENSE
huracanpy-1.3.0.dist-info/METADATA
huracanpy-1.3.0.dist-info/WHEEL
huracanpy-1.3.0.dist-info/top_level.txt
huracanpy-1.3.0.dist-info/RECORD
