Metadata-Version: 2.4
Name: huracanpy
Version: 1.3.0
Summary: A python package for working with various forms of feature tracking data
Author-email: Leo Saffin <l.saffin@reading.ac.uk>, Stella Bourdin <stella.bourdin@physics.ox.ac.uk>
Requires-Python: <3.14,>=3.9
License-File: LICENSE
Requires-Dist: numpy
Requires-Dist: xarray
Requires-Dist: cftime
Requires-Dist: parse
Requires-Dist: shapely
Requires-Dist: pandas
Requires-Dist: geopandas>=0.14.4
Requires-Dist: matplotlib
Requires-Dist: seaborn
Requires-Dist: netcdf4
Requires-Dist: haversine
Requires-Dist: cartopy
Requires-Dist: matplotlib-venn<1
Requires-Dist: metpy
Requires-Dist: tqdm
Requires-Dist: pyarrow
Requires-Dist: pyproj
Provides-Extra: dev
Requires-Dist: pre-commit; extra == "dev"
Requires-Dist: pytest; extra == "dev"
Requires-Dist: pytest-cov; extra == "dev"
Requires-Dist: ruff>=0.9.0; extra == "dev"
Requires-Dist: tox; extra == "dev"
Requires-Dist: nbformat; extra == "dev"
Requires-Dist: nbsphinx; extra == "dev"
Provides-Extra: docs
Requires-Dist: pydata-sphinx-theme; extra == "docs"
Requires-Dist: sphinx-copybutton; extra == "docs"
Requires-Dist: nbsphinx; extra == "docs"
Requires-Dist: IPython; extra == "docs"
Requires-Dist: sphinx-design; extra == "docs"
Requires-Dist: ipykernel; extra == "docs"
Requires-Dist: myst-parser; extra == "docs"
Requires-Dist: sphinx_autosummary_accessors; extra == "docs"
Dynamic: license-file
